{
  "id": "ec329c",
  "title": "Phase 3: Document new concepts",
  "status": "done",
  "type": "feature",
  "priority": 2,
  "labels": [
    "readme-update"
  ],
  "created": "2026-02-15T21:09:05.242307Z",
  "updated": "2026-02-15T21:10:45.638243Z",
  "description": "## Acceptance Criteria\n- [ ] Document user identity (WORK_USER env, git user.name, \"system\" fallback)\n- [ ] Document issue types (feature, bug, chore) with default_type config\n- [ ] Document parent/child relationships (epics) — show displays children, no grandchildren rule\n\n## Context\nPart of: Fix: update README to reflect recent features\nDepends on: Phase 2"
}